panama_ruc_dv_calculator/__init__.py
panama_ruc_dv_calculator/calculate_dv_digit.py
panama_ruc_dv_calculator/provincia.py
panama_ruc_dv_calculator/ruc_finca.py
panama_ruc_dv_calculator/ruc_juridica.py
panama_ruc_dv_calculator/ruc_juridica_nt.py
panama_ruc_dv_calculator/ruc_natural.py
panama_ruc_dv_calculator/ruc_natural_nt.py
panama_ruc_dv_calculator-1.0.4.dist-info/LICENSE
panama_ruc_dv_calculator-1.0.4.dist-info/METADATA
panama_ruc_dv_calculator-1.0.4.dist-info/WHEEL
panama_ruc_dv_calculator-1.0.4.dist-info/top_level.txt
panama_ruc_dv_calculator-1.0.4.dist-info/RECORD
