Metadata-Version: 2.1
Name: panama-ruc-dv-calculator
Version: 1.0.4
Summary: A DV calculator for Panama RUC
Home-page: https://github.com/juancorradine/panama-ruc-dv-calculator
Author: Juan Corradine
Classifier: Programming Language :: Python :: 3
Classifier: License :: OSI Approved :: MIT License
Classifier: Operating System :: OS Independent
Requires-Python: >=3.8
License-File: LICENSE
